package2/__init__.py
test_package_0.0.1-0.0.1.dist-info/LICENSE
test_package_0.0.1-0.0.1.dist-info/METADATA
test_package_0.0.1-0.0.1.dist-info/WHEEL
test_package_0.0.1-0.0.1.dist-info/top_level.txt
test_package_0.0.1-0.0.1.dist-info/RECORD
