Metadata-Version: 2.1
Name: test-package-0.0.1
Version: 0.0.1
Summary: Setting up a sample python package
Home-page: UNKNOWN
Author: sachin
Author-email: reachsachinquick@gmail.com
License: UNKNOWN
Keywords: python,sample package
Platform: UNKNOWN
Classifier: Development Status :: 3 - Alpha
Classifier: Intended Audience :: Education
Classifier: Programming Language :: Python :: 2
Classifier: Programming Language :: Python :: 3
Classifier: Operating System :: MacOS :: MacOS X
Classifier: Operating System :: Microsoft :: Windows
License-File: LICENSE
